scons_xo_exts_lib/Find.py
scons_xo_exts_lib/GenericExtensions.py
scons_xo_exts_lib/Read.py
scons_xo_exts_lib/__init__.py
scons_xo_exts_lib/Actions/Uv.py
scons_xo_exts_lib/Actions/__init__.py
scons_xo_exts_lib/BuildSupport/Make.py
scons_xo_exts_lib/BuildSupport/NodeMangling.py
scons_xo_exts_lib/BuildSupport/__init__.py
scons_xo_exts_lib/Builders/__init__.py
scons_xo_exts_lib/Builders/bazel.py
scons_xo_exts_lib/Builders/cmake.py
scons_xo_exts_lib/Builders/dotnet.py
scons_xo_exts_lib/Builders/dune.py
scons_xo_exts_lib/Builders/elisp.py
scons_xo_exts_lib/Builders/elixir.py
scons_xo_exts_lib/Builders/make.py
scons_xo_exts_lib/Builders/meson.py
scons_xo_exts_lib/Builders/ninjabuild.py
scons_xo_exts_lib/Builders/orgmode.py
scons_xo_exts_lib/Builders/pandoc.py
scons_xo_exts_lib/Builders/racket.py
scons_xo_exts_lib/Builders/scons_external.py
scons_xo_exts_lib/Builders/tar_image.py
scons_xo_exts_lib-1.5.0.dist-info/WHEEL
scons_xo_exts_lib-1.5.0.dist-info/METADATA
scons_xo_exts_lib-1.5.0.dist-info/RECORD
