Metadata-Version: 2.4
Name: scons-xo-exts-lib
Version: 1.5.0
Summary: Scons extensions library by XGQT.
Author-email: Maciej Barć <xgqt@xgqt.org>
Requires-Python: >=3.12
Classifier: Environment :: Console
Classifier: Operating System :: POSIX
Classifier: Programming Language :: Python :: 3 :: Only
Requires-Dist: scons>=4.8.1
Project-URL: Home, https://gitlab.com/xgqt/xgqt-python-lib-scons-xo-exts/
